sweet.py
sweetheart-0.1.dev7.data/scripts/sweet.py
sweetheart-0.1.dev7.dist-info/LICENSE
sweetheart-0.1.dev7.dist-info/METADATA
sweetheart-0.1.dev7.dist-info/WHEEL
sweetheart-0.1.dev7.dist-info/top_level.txt
sweetheart-0.1.dev7.dist-info/RECORD
