Metadata-Version: 2.1
Name: sweetheart
Version: 0.1.dev7
Summary: allow building of full-stacked webapps including AI at the speedlight
Home-page: UNKNOWN
Author: Nicolas Champion
Author-email: champion.nicolas@gmail.com
License: CeCILL-C
Project-URL: Source Code, https://github.com/IncredibleProgress/sweetheart.py
Keywords: ubuntu mongodb starlette webapp industry4.0
Platform: UNKNOWN
Classifier: Environment :: Web Environment
Classifier: Intended Audience :: Manufacturing
Classifier: License :: CeCILL-C Free Software License Agreement (CECILL-C)
Classifier: Operating System :: POSIX :: Linux
Classifier: Operating System :: Microsoft :: Windows :: Windows 10
Classifier: Programming Language :: Python :: 3.6
Classifier: Programming Language :: Python :: 3.7
Classifier: Programming Language :: Python :: 3.8
Classifier: Topic :: Database :: Database Engines/Servers
Classifier: Topic :: Internet :: WWW/HTTP :: HTTP Servers
Classifier: Topic :: Internet :: WWW/HTTP :: Dynamic Content
Classifier: Topic :: Office/Business
Classifier: Topic :: Scientific/Engineering
Classifier: Topic :: Software Development :: User Interfaces
Classifier: Topic :: System :: Installation/Setup
